ksystem/__init__.py
ksystem/core/warehouse.py
ksystem/database/codeDB.py
ksystem/database/productDB.py
ksystem/process/code.py
ksystem-1.7.8.dist-info/METADATA
ksystem-1.7.8.dist-info/WHEEL
ksystem-1.7.8.dist-info/top_level.txt
ksystem-1.7.8.dist-info/RECORD
