Metadata-Version: 2.1
Name: ksystem
Version: 1.7.8
Summary: a system to support kuzhidu
Home-page: https://github.com/zoumingzhe/ksystem
Author: Zou Mingzhe
Author-email: zoumingzhe@qq.com
License: MIT
Platform: any
Classifier: Development Status :: 5 - Production/Stable
Classifier: Intended Audience :: Developers
Classifier: Intended Audience :: End Users/Desktop
Classifier: License :: OSI Approved :: MIT License
Classifier: Natural Language :: Chinese (Simplified)
Classifier: Operating System :: Microsoft :: Windows
Classifier: Programming Language :: Python
Classifier: Programming Language :: Python :: 3
Classifier: Programming Language :: Python :: 3.6
Requires-Dist: ztools (>=2.2.0)
